pyAlgebra.py
PyAlgebraLib-1.0.0.dist-info/LICENSE
PyAlgebraLib-1.0.0.dist-info/METADATA
PyAlgebraLib-1.0.0.dist-info/WHEEL
PyAlgebraLib-1.0.0.dist-info/top_level.txt
PyAlgebraLib-1.0.0.dist-info/RECORD
