Metadata-Version: 2.1
Name: PyAlgebraLib
Version: 1.0.0
Summary: Simple and native python program to perform algebra operations using the most efficient algorithms.
Author-email: Rodrigo Martin Núñez <rodrigomartinnunez@gmail.com>
Maintainer-email: Rodrigo Martin Núñez <rodrigomartinnunez@gmail.com>
License: MIT License
Project-URL: Homepage, https://github.com/P-ict0/PyAlgebraLib.git
Project-URL: Bug Reports, https://github.com/P-ict0/PyAlgebraLib/issues
Keywords: algebra,math,development,library,algorithms
Classifier: Development Status :: 3 - Alpha
Classifier: Intended Audience :: Developers
Classifier: Topic :: Software Development :: Build Tools
Classifier: License :: OSI Approved :: GNU General Public License v3 (GPLv3)
Classifier: Programming Language :: Python :: 3
Classifier: Programming Language :: Python :: 3.10
Classifier: Programming Language :: Python :: 3.11
Requires-Python: >=3.10
License-File: LICENSE
